odoo/addons/mrp_subcontracting_purchase/README.rst
odoo/addons/mrp_subcontracting_purchase/__init__.py
odoo/addons/mrp_subcontracting_purchase/__manifest__.py
odoo/addons/mrp_subcontracting_purchase/data/mrp_subcontracting_dropshipping_data.xml
odoo/addons/mrp_subcontracting_purchase/demo/bom_subcontract_demo.xml
odoo/addons/mrp_subcontracting_purchase/demo/partner_subcontract_demo.xml
odoo/addons/mrp_subcontracting_purchase/demo/product_category_demo.xml
odoo/addons/mrp_subcontracting_purchase/demo/product_product_demo.xml
odoo/addons/mrp_subcontracting_purchase/demo/product_supplierinfo_demo.xml
odoo/addons/mrp_subcontracting_purchase/demo/stock_location_demo.xml
odoo/addons/mrp_subcontracting_purchase/demo/stock_rules_demo.xml
odoo/addons/mrp_subcontracting_purchase/i18n/it.po
odoo/addons/mrp_subcontracting_purchase/i18n/mrp_subcontracting_purchase.pot
odoo/addons/mrp_subcontracting_purchase/models/__init__.py
odoo/addons/mrp_subcontracting_purchase/models/mrp_production.py
odoo/addons/mrp_subcontracting_purchase/models/purchase_order.py
odoo/addons/mrp_subcontracting_purchase/models/purchase_order_line.py
odoo/addons/mrp_subcontracting_purchase/models/res_company.py
odoo/addons/mrp_subcontracting_purchase/models/stock_move.py
odoo/addons/mrp_subcontracting_purchase/models/stock_picking.py
odoo/addons/mrp_subcontracting_purchase/models/stock_rule.py
odoo/addons/mrp_subcontracting_purchase/models/stock_warehouse.py
odoo/addons/mrp_subcontracting_purchase/readme/CONFIGURE.md
odoo/addons/mrp_subcontracting_purchase/readme/CONTRIBUTORS.md
odoo/addons/mrp_subcontracting_purchase/readme/DESCRIPTION.md
odoo/addons/mrp_subcontracting_purchase/readme/HISTORY.md
odoo/addons/mrp_subcontracting_purchase/static/description/icon.png
odoo/addons/mrp_subcontracting_purchase/static/description/index.html
odoo/addons/mrp_subcontracting_purchase/tests/__init__.py
odoo/addons/mrp_subcontracting_purchase/tests/test_mrp_production.py
odoo14_addon_mrp_subcontracting_purchase-14.0.1.0.1.dist-info/METADATA
odoo14_addon_mrp_subcontracting_purchase-14.0.1.0.1.dist-info/WHEEL
odoo14_addon_mrp_subcontracting_purchase-14.0.1.0.1.dist-info/top_level.txt
odoo14_addon_mrp_subcontracting_purchase-14.0.1.0.1.dist-info/RECORD
